<?xml version="1.0" encoding="UTF-8"?>

<Defs>

<TraderKindDef>
<defName>Caravan_PFBrotherhood_BulkGoods</defName>
<label>Bulk Goods Trader</label>
<stockGenerators>
<li Class="StockGenerator_SingleDef">
<thingDef>Silver</thingDef>
<countRange>
<min>1200</min>
<max>2500</max>
</countRange>
</li>
<li Class="StockGenerator_SingleDef">
<thingDef>ComponentIndustrial</thingDef>
<countRange>
<min>5</min>
<max>15</max>
</countRange>
</li>
<li Class="StockGenerator_SingleDef">
<thingDef>ComponentSpacer</thingDef>
<countRange>
<min>1</min>
<max>2</max>
</countRange>
</li>
<li Class="StockGenerator_SingleDef">
<thingDef>Steel</thingDef>
<price>Cheap</price>
<countRange>
<min>125</min>
<max>350</max>
</countRange>
</li>
<li Class="StockGenerator_SingleDef">
<thingDef>WoodLog</thingDef>
<price>Cheap</price>
<countRange>
<min>100</min>
<max>200</max>
</countRange>
</li>
<li Class="StockGenerator_SingleDef">
<thingDef>Plasteel</thingDef>
<price>Cheap</price>
<countRange>
<min>75</min>
<max>200</max>
</countRange>
</li>
<li Class="StockGenerator_SingleDef">
<thingDef>Cloth</thingDef>
<price>Normal</price>
<countRange>
<min>-50</min>
<max>120</max>
</countRange>
</li>
<li Class="StockGenerator_SingleDef">
<thingDef>Gold</thingDef>
<price>Normal</price>
<countRange>
<min>-40</min>
<max>120</max>
</countRange>
</li>
<li Class="StockGenerator_Category">
<categoryDef>Textiles</categoryDef>
<thingDefCountRange>
<min>2</min>
<max>3</max>
</thingDefCountRange>
<price>Cheap</price>
<totalPriceRange>
<min>500</min>
<max>1000</max>
</totalPriceRange>
</li>
<li Class="StockGenerator_Category">
<categoryDef>ResourcesRaw</categoryDef>
<thingDefCountRange>
<min>2</min>
<max>5</max>
</thingDefCountRange>
<price>Cheap</price>
<totalPriceRange>
<min>150</min>
<max>350</max>
</totalPriceRange>
</li>
<li Class="StockGenerator_Category">
<categoryDef>FoodRaw</categoryDef>
<thingDefCountRange>
<min>2</min>
<max>4</max>
</thingDefCountRange>
<price>Cheap</price>
<totalPriceRange>
<min>150</min>
<max>600</max>
</totalPriceRange>
</li>
<li Class="StockGenerator_Category">
<categoryDef>FoodMeals</categoryDef>
<thingDefCountRange>
<min>1</min>
<max>2</max>
</thingDefCountRange>
<price>Cheap</price>
<totalPriceRange>
<min>200</min>
<max>600</max>
</totalPriceRange>
</li>
<li Class="StockGenerator_SingleDef">
<thingDef>MedicineIndustrial</thingDef>
<countRange>
<min>15</min>
<max>25</max>
</countRange>
</li>
<li Class="StockGenerator_Tag">
<tradeTag>Furnature</tradeTag>
<thingDefCountRange>
<min>0</min>
<max>2</max>
</thingDefCountRange>
<countRange>
<min>-1</min>
<max>2</max>
</countRange>
</li>
<li Class="StockGenerator_BuyWeirdOrganic"/>
</stockGenerators>

</TraderKindDef>

<TraderKindDef>
<defName>Caravan_PFBrotherhood_TechSupplier</defName>
<label>Tech Supplier</label>
<stockGenerators>
<li Class="StockGenerator_SingleDef">
<thingDef>Silver</thingDef>
<countRange>
<min>1200</min>
<max>2500</max>
</countRange>
</li>
<li Class="StockGenerator_SingleDef">
<thingDef>ComponentIndustrial</thingDef>
<countRange>
<min>-2</min>
<max>10</max>
</countRange>
</li>
<li Class="StockGenerator_SingleDef">
<thingDef>ComponentSpacer</thingDef>
<countRange>
<min>2</min>
<max>3</max>
</countRange>
</li>
<li Class="StockGenerator_WeaponsRanged">
<countRange>
<min>4</min>
<max>8</max>
</countRange>
</li>
<li Class="StockGenerator_Armor">
<countRange>
<min>1</min>
<max>2</max>
</countRange>
</li>
<li Class="StockGenerator_SingleDef">
<thingDef>MedicineUltratech</thingDef>
<countRange>
<min>5</min>
<max>20</max>
</countRange>
</li>
<li Class="StockGenerator_Tag">
<tradeTag>BodyPartOrImplant</tradeTag>
<thingDefCountRange>
<min>-1</min>
<max>3</max>
</thingDefCountRange>
<countRange>
<min>1</min>
<max>2</max>
</countRange>
</li>
<li Class="StockGenerator_SingleDef">
<thingDef>PFFocusLens</thingDef>
<price>Normal</price>
<countRange>
<min>1</min>
<max>3</max>
</countRange>
</li>
<li Class="StockGenerator_SingleDef">
<thingDef>PFSuperconductor</thingDef>
<price>Normal</price>
<countRange>
<min>1</min>
<max>3</max>
</countRange>
</li>
<li Class="StockGenerator_Tag">
<tradeTag>Artifact</tradeTag>
<thingDefCountRange>
<min>1</min>
<max>2</max>
</thingDefCountRange>
<countRange>
<min>1</min>
<max>1</max>
</countRange>
</li>
<li Class="StockGenerator_BuyWeirdOrganic"/>
</stockGenerators>
</TraderKindDef>

<TraderKindDef>
<defName>Caravan_PFBrotherhood_Exotic</defName>
<label>Exotic Good Trader</label>
<stockGenerators>
<li Class="StockGenerator_SingleDef">
<thingDef>Silver</thingDef>
<countRange>
<min>1750</min>
<max>4000</max>
</countRange>
</li>
<li Class="StockGenerator_SingleDef">
<thingDef>ComponentIndustrial</thingDef>
<countRange>
<min>8</min>
<max>24</max>
</countRange>
</li>
<li Class="StockGenerator_SingleDef">
<thingDef>ComponentSpacer</thingDef>
<countRange>
<min>2</min>
<max>4</max>
</countRange>
</li>
<li Class="StockGenerator_SingleDef">
<thingDef>Plasteel</thingDef>
<price>Cheap</price>
<countRange>
<min>75</min>
<max>200</max>
</countRange>
</li>
<li Class="StockGenerator_SingleDef">
<thingDef>Gold</thingDef>
<price>Normal</price>
<countRange>
<min>100</min>
<max>250</max>
</countRange>
</li>
<li Class="StockGenerator_SingleDef">
<thingDef>MedicineUltratech</thingDef>
<countRange>
<min>-2</min>
<max>5</max>
</countRange>
</li>
<li Class="StockGenerator_Tag">
<tradeTag>Exotic</tradeTag>
<thingDefCountRange>
<min>2</min>
<max>4</max>
</thingDefCountRange>
<countRange>
<min>1</min>
<max>2</max>
</countRange>
</li>
<li Class="StockGenerator_Tag">
<tradeTag>BodyPartOrImplant</tradeTag>
<thingDefCountRange>
<min>2</min>
<max>5</max>
</thingDefCountRange>
<countRange>
<min>1</min>
<max>2</max>
</countRange>
</li>
<li Class="StockGenerator_SingleDef">
<thingDef>PFFocusLens</thingDef>
<price>Normal</price>
<countRange>
<min>1</min>
<max>3</max>
</countRange>
</li>
<li Class="StockGenerator_SingleDef">
<thingDef>PFSuperconductor</thingDef>
<price>Normal</price>
<countRange>
<min>1</min>
<max>3</max>
</countRange>
</li>
<li Class="StockGenerator_Tag">
<tradeTag>Artifact</tradeTag>
<thingDefCountRange>
<min>1</min>
<max>2</max>
</thingDefCountRange>
<countRange>
<min>1</min>
<max>1</max>
</countRange>
</li>
<li Class="StockGenerator_Category">
<categoryDef>Apparel</categoryDef>
<thingDefCountRange>
<min>1</min>
<max>3</max>
</thingDefCountRange>
<totalPriceRange>
<min>500</min>
<max>1800</max>
</totalPriceRange>
<countRange>
<min>1</min>
<max>2</max>
</countRange>
</li>
<li Class="StockGenerator_Art">
<countRange>
<min>1</min>
<max>3</max>
</countRange>
</li>
<li Class="StockGenerator_Tag">
<tradeTag>Television</tradeTag>
<thingDefCountRange>
<min>1</min>
<max>2</max>
</thingDefCountRange>
<countRange>
<min>-2</min>
<max>2</max>
</countRange>
</li>
<li Class="StockGenerator_SingleDef">
<thingDef>Telescope</thingDef>
<countRange>
<min>-2</min>
<max>2</max>
</countRange>
</li>
<li Class="StockGenerator_Tag">
<tradeTag>Furnature</tradeTag>
<thingDefCountRange>
<min>0</min>
<max>3</max>
</thingDefCountRange>
<countRange>
<min>-1</min>
<max>2</max>
</countRange>
</li>
<li Class="StockGenerator_BuyWeirdOrganic"/>
</stockGenerators>

</TraderKindDef>

<TraderKindDef>
<defName>Visitor_Vault_Standard</defName>
<label>Trader</label>
<stockGenerators>
<li Class="StockGenerator_SingleDef">
<thingDef>Silver</thingDef>
<countRange>
<min>50</min>
<max>300</max>
</countRange>
</li>
<li Class="StockGenerator_SingleDef">
<thingDef>ComponentIndustrial</thingDef>
<countRange>
<min>-2</min>
<max>5</max>
</countRange>
</li>
<li Class="StockGenerator_Category">
<categoryDef>FoodMeals</categoryDef>
<thingDefCountRange>
<min>1</min>
<max>2</max>
</thingDefCountRange>
<countRange>
<min>0</min>
<max>3</max>
</countRange>
</li>
<li Class="StockGenerator_SingleDef">
<thingDef>MedicineIndustrial</thingDef>
<countRange>
<min>0</min>
<max>6</max>
</countRange>
</li>
<li Class="StockGenerator_WeaponsRanged">
<countRange>
<min>0</min>
<max>2</max>
</countRange>
</li><li Class="StockGenerator_BuyWeirdOrganic"/>
</stockGenerators>
</TraderKindDef>

<TraderKindDef>
<defName>Visitor_PFBrotherhood_Standard</defName>
<label>Trader</label>
<stockGenerators>
<li Class="StockGenerator_SingleDef">
<thingDef>Silver</thingDef>
<countRange>
<min>50</min>
<max>300</max>
</countRange>
</li>
<li Class="StockGenerator_SingleDef">
<thingDef>ComponentIndustrial</thingDef>
<countRange>
<min>-2</min>
<max>5</max>
</countRange>
</li>
<li Class="StockGenerator_Category">
<categoryDef>FoodMeals</categoryDef>
<thingDefCountRange>
<min>1</min>
<max>2</max>
</thingDefCountRange>
<countRange>
<min>0</min>
<max>3</max>
</countRange>
</li>
<li Class="StockGenerator_SingleDef">
<thingDef>MedicineIndustrial</thingDef>
<countRange>
<min>0</min>
<max>6</max>
</countRange>
</li>
<li Class="StockGenerator_WeaponsRanged">
<countRange>
<min>0</min>
<max>2</max>
</countRange>
</li><li Class="StockGenerator_BuyWeirdOrganic"/>
</stockGenerators>
</TraderKindDef>

</Defs>